pandas_trader/__init__.py
pandas_trader/extras.py
pandas_trader/functionalities.py
pandas_trader/ohlc_accessor.py
pandas_trader/options_accessor.py
pandas_trader-0.1.4.dist-info/METADATA
pandas_trader-0.1.4.dist-info/WHEEL
pandas_trader-0.1.4.dist-info/RECORD
