Metadata-Version: 2.1
Name: pandas-trader
Version: 0.1.4
Summary: Trading and backtesting in Pandas.
Home-page: https://github.com/lucasjamar/pandas-trader
License: Apache-2.0
Keywords: Trading,Backtesting,Pandas
Author: Lucas Jamar
Author-email: lucasjamar47@gmail.com
Requires-Python: >=3.9,<4.0
Classifier: License :: OSI Approved :: Apache Software License
Classifier: Programming Language :: Python :: 3
Classifier: Programming Language :: Python :: 3.9
Classifier: Programming Language :: Python :: 3.10
Classifier: Programming Language :: Python :: 3.11
Classifier: Programming Language :: Python :: 3.12
Requires-Dist: pandas[computation] (>=2.2.0,<3.0.0)
Project-URL: Repository, https://github.com/lucasjamar/pandas-trader
